birdhousebuilder.recipe.nginx-0.3.6-py2.7-nspkg.pth
birdhousebuilder/recipe/nginx/README.txt
birdhousebuilder/recipe/nginx/__init__.py
birdhousebuilder/recipe/nginx/mime.types
birdhousebuilder/recipe/nginx/nginx.conf
birdhousebuilder/recipe/nginx/tests/__init__.py
birdhousebuilder/recipe/nginx/tests/test_doctests.py
birdhousebuilder.recipe.nginx-0.3.6.dist-info/DESCRIPTION.rst
birdhousebuilder.recipe.nginx-0.3.6.dist-info/METADATA
birdhousebuilder.recipe.nginx-0.3.6.dist-info/RECORD
birdhousebuilder.recipe.nginx-0.3.6.dist-info/WHEEL
birdhousebuilder.recipe.nginx-0.3.6.dist-info/entry_points.txt
birdhousebuilder.recipe.nginx-0.3.6.dist-info/metadata.json
birdhousebuilder.recipe.nginx-0.3.6.dist-info/namespace_packages.txt
birdhousebuilder.recipe.nginx-0.3.6.dist-info/pbr.json
birdhousebuilder.recipe.nginx-0.3.6.dist-info/top_level.txt
