Metadata-Version: 2.0
Name: birdhousebuilder.recipe.nginx
Version: 0.3.6
Summary: A Buildout recipe to install and configure Nginx with conda.
Home-page: https://github.com/bird-house/birdhousebuilder.recipe.nginx
Author: Birdhouse
Author-email: UNKNOWN
License: Apache License 2
Keywords: buildout recipe birdhouse nginx conda
Platform: UNKNOWN
Classifier: Framework :: Buildout
Classifier: Intended Audience :: Developers
Classifier: Topic :: Software Development :: Build Tools
Classifier: Topic :: Software Development :: Libraries :: Python Modules
Classifier: License :: OSI Approved :: BSD License
Requires-Dist: birdhousebuilder.recipe.conda
Requires-Dist: birdhousebuilder.recipe.supervisor
Requires-Dist: mako
Requires-Dist: pyopenssl
Requires-Dist: setuptools
Requires-Dist: zc.buildout
Requires-Dist: zc.recipe.deployment
Provides-Extra: tests
Requires-Dist: zc.buildout; extra == 'tests'
Requires-Dist: zope.testing; extra == 'tests'
